[
  {
    "title": "'재계 6위'로 다시 후퇴…롯데, 본업 회복에 희망 걸었다",
    "description": "롯데그룹의 재계 순위가 1년 만에 다시 6위로 내려앉았다. 지난해 토지 자산 재평가를 통해 5위 자리를 되찾았지만 비핵심 자산 매각 등 구조조정을 진행하면서 자산총액이 감소한 영향이다. 뼈를 깎는 구조조정에도...",
    "url": "https://n.news.naver.com/mnews/article/648/0000047034?sid=101",
    "originallink": "https://news.bizwatch.co.kr/article/consumer/2026/05/11/0038",
    "source": "비즈워치",
    "published_at": "Tue, 12 May 2026 07:20:00 +0900",
    "published_at_kst": "2026-05-12T07:20:00+09:00",
    "keyword": "롯데그룹",
    "sort": "date",
    "scraped_at": "2026-05-12T08:02:01.187108+09:00",
    "importance_score": 4,
    "category": "그룹전략",
    "content": "롯데그룹의 재계 순위가 1년 만에 다시 6위로 내려앉았다. 지난해 토지 자산 재평가를 통해 5위 자리를 되찾았지만 비핵심 자산 매각 등 구조조정을 진행하면서 자산총액이 감소한 영향이다. 뼈를 깎는 구조조정에도..."
  },
  {
    "title": "SI 업계, 1분기 'AI·클라우드' 바람 타고 호실적…수익성 대폭 개선",
    "description": "롯데이노베이트의 1분기 매출은 2811억7800만원으로 전년 대비 1.3% 감소했지만, 영업이익은 97억3600만원으로 39.9% 증가했다. 시스템통합(SI) 부문 수익성 개선과 시스템운영(SM) 부문 외형 확대가 동시에 작용했다. 회사...",
    "url": "https://www.newspim.com/news/view/20260511001205",
    "originallink": "https://www.newspim.com/news/view/20260511001205",
    "source": "뉴스핌",
    "published_at": "Mon, 11 May 2026 17:36:00 +0900",
    "published_at_kst": "2026-05-11T17:36:00+09:00",
    "keyword": "롯데이노베이트",
    "sort": "date",
    "scraped_at": "2026-05-12T08:02:01.187108+09:00",
    "importance_score": 4,
    "category": "롯데이노베이트",
    "content": "롯데이노베이트의 1분기 매출은 2811억7800만원으로 전년 대비 1.3% 감소했지만, 영업이익은 97억3600만원으로 39.9% 증가했다. 시스템통합(SI) 부문 수익성 개선과 시스템운영(SM) 부문 외형 확대가 동시에 작용했다. 회사..."
  },
  {
    "title": "롯데쇼핑, 1분기 영업이익 70%↑…백화점 ‘역대 최대’",
    "description": "주력 사업인 백화점이 역대 최대 실적을 갈아치운 가운데, 만성 적자에 시달리던 계열사들도 수익성을 회복하며 반등세를 보이고 있습니다. 이혜연 기자입니다. 롯데쇼핑이 백화점의 폭발적인 성장과 주요 사업부의...",
    "url": "https://www.sentv.co.kr/article/view/sentv202605110057",
    "originallink": "https://www.sentv.co.kr/article/view/sentv202605110057",
    "source": "서울경제TV",
    "published_at": "Mon, 11 May 2026 18:10:00 +0900",
    "published_at_kst": "2026-05-11T18:10:00+09:00",
    "keyword": "롯데계열사",
    "sort": "date",
    "scraped_at": "2026-05-12T08:02:01.187108+09:00",
    "importance_score": 4,
    "category": "실적",
    "content": "주력 사업인 백화점이 역대 최대 실적을 갈아치운 가운데, 만성 적자에 시달리던 계열사들도 수익성을 회복하며 반등세를 보이고 있습니다. 이혜연 기자입니다. 롯데쇼핑이 백화점의 폭발적인 성장과 주요 사업부의..."
  },
  {
    "title": "점포 줄이고 PB 키웠지만…남창희號 롯데하이마트, 본업 경쟁력 ‘흔들...",
    "description": "롯데하이마트 역시 2012년 롯데그룹 편입 이후 2017년까지 4조원대 매출과 2000억원이 넘는 영업이익을 기록했지만, 지난해에는 매출 2조3001억원, 영업이익 96억원까지 쪼그라들었다. 이에 2022년 말부터 롯데하이마트를...",
    "url": "https://www.ceoscoredaily.com/page/view/2026051116003063049",
    "originallink": "https://www.ceoscoredaily.com/page/view/2026051116003063049",
    "source": "ceoscoredaily",
    "published_at": "Tue, 12 May 2026 07:00:00 +0900",
    "published_at_kst": "2026-05-12T07:00:00+09:00",
    "keyword": "롯데그룹",
    "sort": "date",
    "scraped_at": "2026-05-12T08:02:01.187108+09:00",
    "importance_score": 3,
    "category": "그룹전략",
    "content": "롯데하이마트 역시 2012년 롯데그룹 편입 이후 2017년까지 4조원대 매출과 2000억원이 넘는 영업이익을 기록했지만, 지난해에는 매출 2조3001억원, 영업이익 96억원까지 쪼그라들었다. 이에 2022년 말부터 롯데하이마트를..."
  },
  {
    "title": "계열사만으론 한계…제일기획·이노션, 외부 광고주 확보 총력",
    "description": "롯데그룹 계열 광고사 대홍기획 역시 SK이노베이션과 넥슨 등을 신규 고객사로 확보하며 비계열 매출 비중을 60% 수준까지 높였다. LG그룹 광고 계열사 HSAD도 두나무와 제이시스메디칼 등을 신규 고객으로 유치하며 금융...",
    "url": "https://n.news.naver.com/mnews/article/011/0004619723?sid=101",
    "originallink": "https://www.sedaily.com/article/20042765?ref=naver",
    "source": "서울경제",
    "published_at": "Tue, 12 May 2026 06:58:00 +0900",
    "published_at_kst": "2026-05-12T06:58:00+09:00",
    "keyword": "롯데그룹",
    "sort": "date",
    "scraped_at": "2026-05-12T08:02:01.187108+09:00",
    "importance_score": 3,
    "category": "그룹전략",
    "content": "롯데그룹 계열 광고사 대홍기획 역시 SK이노베이션과 넥슨 등을 신규 고객사로 확보하며 비계열 매출 비중을 60% 수준까지 높였다. LG그룹 광고 계열사 HSAD도 두나무와 제이시스메디칼 등을 신규 고객으로 유치하며 금융..."
  },
  {
    "title": "명동에 K콘텐츠 다 모았다..롯데백화점, 롯데타운 명동 페스티벌 개최",
    "description": "또한 15일부터 25일까지 롯데호텔 서울의 야외 광장에서는 롯데호텔, 롯데면세점, 롯데칠성음료, 롯데홈쇼핑 등 롯데그룹의 대표 계열사들이 참여한다. 각 사업별 개성을 반영한 FB 및 굿즈 등을 선보이는 LTM 마켓도...",
    "url": "https://kpenews.com/View.aspx?No=4074025",
    "originallink": "https://kpenews.com/View.aspx?No=4074025",
    "source": "한국정경신문",
    "published_at": "Tue, 12 May 2026 07:52:00 +0900",
    "published_at_kst": "2026-05-12T07:52:00+09:00",
    "keyword": "롯데그룹",
    "sort": "date",
    "scraped_at": "2026-05-12T08:02:01.187108+09:00"
  },
  {
    "title": "명동에 대규모 ‘K-방탈출’ 열린다…롯데백화점의 새도전",
    "description": "행사 기간 롯데호텔 서울의 야외 광장에서는 롯데호텔, 롯데면세점, 롯데칠성음료, 롯데홈쇼핑 등 롯데그룹의 대표 계열사들이 참여해 사업별 개성을 반영한 F&B와 굿즈를 선보이는 ‘LTM 마켓’도 운영한다. 김준세...",
    "url": "https://n.news.naver.com/mnews/article/016/0002641910?sid=101",
    "originallink": "https://biz.heraldcorp.com/article/10735601?ref=naver",
    "source": "헤럴드경제",
    "published_at": "Tue, 12 May 2026 07:25:00 +0900",
    "published_at_kst": "2026-05-12T07:25:00+09:00",
    "keyword": "롯데그룹",
    "sort": "date",
    "scraped_at": "2026-05-12T08:02:01.187108+09:00"
  },
  {
    "title": "50대 그룹 시총 5년새 187%↑…공정자산 규모 첫 추월",
    "description": "한화그룹은 올해 롯데를 제치고 처음으로 5대 그룹에 올랐다. HD현대도 9위에서 8위로 한 계단 상승했다. 반면 롯데는 5위에서 6위, 포스코는 6위에서 7위, GS는 8위에서 10위로 각각 밀려났다. 10대 그룹...",
    "url": "https://n.news.naver.com/mnews/article/003/0013938323?sid=101",
    "originallink": "https://www.newsis.com/view/NISX20260511_0003624935",
    "source": "뉴시스",
    "published_at": "Tue, 12 May 2026 06:00:00 +0900",
    "published_at_kst": "2026-05-12T06:00:00+09:00",
    "keyword": "롯데그룹",
    "sort": "date",
    "scraped_at": "2026-05-12T08:02:01.187108+09:00"
  },
  {
    "title": "'제2의 스페이스X' 찾는 증권가… 어디 투자했나 보니",
    "description": "평가손익 확대에 가장 크게 이바지한 법인(계열사 및 경영참가 법인 제외)은 우리금융지주였다.... 그밖에 SK온(지분 0.7%), 롯데글로벌로지스(14.0%), 카카오모빌리티(0.2%), 직방(0.5%), 비바리퍼블리카 우선주 등...",
    "url": "https://it.chosun.com/news/articleView.html?idxno=2023092161860",
    "originallink": "https://it.chosun.com/news/articleView.html?idxno=2023092161860",
    "source": "조선일보",
    "published_at": "Tue, 12 May 2026 06:02:00 +0900",
    "published_at_kst": "2026-05-12T06:02:00+09:00",
    "keyword": "롯데계열사",
    "sort": "date",
    "scraped_at": "2026-05-12T08:02:01.187108+09:00"
  },
  {
    "title": "롯데장학재단, '제3회 신격호샤롯데문학상' 공모 시작…총 상금 9000만원",
    "description": "롯데장학재단(이사장 장혜선)은 고(故) 신격호 롯데그룹 창업주의 문학 정신을 기리기 위한 '제 3회 신격호샤롯데문학상' 작품 공모를 실시한다고 11일 밝혔다. 이번 공모는 △소설(단·중편) △시(시조) △수필 3개...",
    "url": "https://www.ksilbo.co.kr/news/articleView.html?idxno=1056468",
    "originallink": "https://www.ksilbo.co.kr/news/articleView.html?idxno=1056468",
    "source": "ksilbo",
    "published_at": "Tue, 12 May 2026 00:44:00 +0900",
    "published_at_kst": "2026-05-12T00:44:00+09:00",
    "keyword": "롯데그룹",
    "sort": "date",
    "scraped_at": "2026-05-12T08:02:01.187108+09:00"
  }
]