[
  {
    "title": "GS는 서초진흥 잡고 한화는 수익성 개선 [주간 빌드업]",
    "description": "GS건설은 서울 서초진흥아파트 재건축을 따냈고, ㈜한화 건설부문은 1분기 수익성이 개선된 실적을 내놨다. 1분기 해외건설 수주액은 중동 부진에 지난해보다 75% 가량 줄어든 것으로 나타났다. ■ GS건설...",
    "url": "https://n.news.naver.com/mnews/article/123/0002382691?sid=101",
    "published_at": "Fri, 08 May 2026 17:53:00 +0900",
    "published_at_kst": "2026-05-08T17:53:00+09:00",
    "keyword": "서울 아파트",
    "scraped_at": "2026-05-08T17:57:25.747856+09:00"
  },
  {
    "title": "“아파트 상승률 압도한 코스피”…코스피 시총 6143조, 전국 아파트 시...",
    "description": "서울 아파트 시총 역시 같은 기간 2241조 원에서 2293조 원으로 2.32% 늘어났다. 지난해 6월과 10월 정부가 잇따라 대출 규제를 강화한 데다 다주택자 매물이 출회되면서 부동산 시장 상승세가 둔화된 영향으로...",
    "url": "https://n.news.naver.com/mnews/article/011/0004618865?sid=101",
    "published_at": "Fri, 08 May 2026 17:53:00 +0900",
    "published_at_kst": "2026-05-08T17:53:00+09:00",
    "keyword": "서울 아파트",
    "scraped_at": "2026-05-08T17:57:25.747856+09:00"
  },
  {
    "title": "서울 아파트 낙찰가율 3개월 만에 반등",
    "description": "지난달 경매로 나온 서울 아파트의 낙찰률(경매 건수 대비 낙찰 건수 비율)이 48.7%를 기록하며 5개월 만에 최고치를 나타냈다. 15억원 이하 아파트 경매 참여자가 늘면서 낙찰가율도 3개월 만에 다시 반등했다....",
    "url": "https://n.news.naver.com/mnews/article/015/0005284706?sid=101",
    "published_at": "Fri, 08 May 2026 17:53:00 +0900",
    "published_at_kst": "2026-05-08T17:53:00+09:00",
    "keyword": "서울 아파트",
    "scraped_at": "2026-05-08T17:57:25.747856+09:00"
  },
  {
    "title": "양도세 중과 부활…3주택자 '마래푸' 팔면 5.6억→12.5억",
    "description": "아실에 따르면 서울의 아파트 매물은 8일 기준 한 달 전보다 10.2% 감소했다. 김용범 청와대 정책실장도 지난 4일 “문재인 정부가 양도세 중과세율을 높인 2021년 6월께 매물이 약 21% 감소했다”며 “(이번에도...",
    "url": "https://n.news.naver.com/mnews/article/015/0005284705?sid=101",
    "published_at": "Fri, 08 May 2026 17:53:00 +0900",
    "published_at_kst": "2026-05-08T17:53:00+09:00",
    "keyword": "서울 아파트",
    "scraped_at": "2026-05-08T17:57:25.747856+09:00"
  },
  {
    "title": "노원구, '하천변 특화 정원' 조성",
    "description": "서울 노원구(구청장 오승록)가 생활 속 걷기 활성화를 위해 지역 내 하천변 산책로에 봄꽃을 식재하고... 당현천은 중랑천에 비해 길이가 짧지만, 하천의 양안(兩岸)에 아파트 단지가 줄 이어 인접해 있어 걷기 활동의...",
    "url": "http://www.enewstoday.co.kr/news/articleView.html?idxno=2427402",
    "published_at": "Fri, 08 May 2026 17:52:00 +0900",
    "published_at_kst": "2026-05-08T17:52:00+09:00",
    "keyword": "서울 아파트",
    "scraped_at": "2026-05-08T17:57:25.747856+09:00"
  },
  {
    "title": "[통계로 보는 부동산] 비규제 지역으로 쏠리는 수도권 수요…구리·하남...",
    "description": "아주경제=우주성 기자 wjs89@ajunews.com 수도권 아파트 시장에서 규제 여부에 따른 희비가 뚜렷해지고 있다. 서울 핵심 규제지역과 과천 등 조정대상지역에서 거래가 급감하는 사이, 구리·하남·안양 만안구 등 비규제...",
    "url": "https://www.ajunews.com/view/20260508174125357",
    "published_at": "Fri, 08 May 2026 17:48:00 +0900",
    "published_at_kst": "2026-05-08T17:48:00+09:00",
    "keyword": "서울 아파트",
    "scraped_at": "2026-05-08T17:57:25.747856+09:00"
  },
  {
    "title": "\"용산을 유엔 AI허브로 글로벌 벤처·VC 유치\"",
    "description": "정원오 민주당 서울시장 후보 '강남4구 특위' 구성도 제안 재개발·재건축 사업 '속도' 무료 예방접종 60세로... 정 후보는 이날 재건축 사업이 추진되고 있는 강남구 개포우성7차 아파트를 직접 방문해 추진 현황을...",
    "url": "https://n.news.naver.com/mnews/article/009/0005677270?sid=100",
    "published_at": "Fri, 08 May 2026 17:48:00 +0900",
    "published_at_kst": "2026-05-08T17:48:00+09:00",
    "keyword": "서울 아파트",
    "scraped_at": "2026-05-08T17:57:25.747856+09:00"
  },
  {
    "title": "\"주택 31만가구 공급 강북엔 용적률 혜택\"",
    "description": "서울의 심각한 주택 부족 문제, 특히 아파트 부족 문제를 해결할 수 있는 건 자신뿐이라는 점을 누차 강조하고 있다. 오 후보는 우선 2031년까지 신축 주택 31만가구를 공급하겠다고 약속했다. 이는 재건축·재개발 등을...",
    "url": "https://n.news.naver.com/mnews/article/009/0005677271?sid=100",
    "published_at": "Fri, 08 May 2026 17:48:00 +0900",
    "published_at_kst": "2026-05-08T17:48:00+09:00",
    "keyword": "서울 아파트",
    "scraped_at": "2026-05-08T17:57:25.747856+09:00"
  },
  {
    "title": "\"10억 전후 서울 아파트 산다면 … 초등학생 많은 대단지 노려라\"",
    "description": "의견 \"서울 지역 중저가 아파트는 지붕이 있는 시장이에요. 실거주 가치가 강하기 때문에 상승 여력이 상대적으로 제한적이라는 뜻이에요. 똑같은 가격이라면 투자 가치가 그래도 있는 단지를 고르는 게 좋습니다....",
    "url": "https://n.news.naver.com/mnews/article/009/0005677258?sid=101",
    "published_at": "Fri, 08 May 2026 17:47:00 +0900",
    "published_at_kst": "2026-05-08T17:47:00+09:00",
    "keyword": "서울 아파트",
    "scraped_at": "2026-05-08T17:57:25.747856+09:00"
  },
  {
    "title": "\"급매 더 나온다, 5~10% 싼 집 노려라\"",
    "description": "한국부동산원에 따르면 5월 첫째 주(4일 기준) 서울 아파트 전세 가격은 전주 대비 0.23% 올라 2015년 11월 셋째 주 이후 가장 높은 상승률을 기록했다. 실수요자라면 서울 지역에서 10억원 안팎의 아파트를 찾아보라는 조언이...",
    "url": "https://n.news.naver.com/mnews/article/009/0005677261?sid=101",
    "published_at": "Fri, 08 May 2026 17:47:00 +0900",
    "published_at_kst": "2026-05-08T17:47:00+09:00",
    "keyword": "서울 아파트",
    "scraped_at": "2026-05-08T17:57:25.747856+09:00"
  },
  {
    "title": "\"임대사업자 양도세 혜택 과도\"… 축소 시사",
    "description": "부동산관계장관회의 구윤철 부총리 \"조세 형평성 차원에서 다양한 방안 검토\" 정부가 서울·수도권의 주택 공급 확대에 주력한다는 방침 아래에 조정대상지역 매입임대 아파트 사업자의 양도소득세 중과 배제 혜택에 대한...",
    "url": "https://n.news.naver.com/mnews/article/009/0005677247?sid=101",
    "published_at": "Fri, 08 May 2026 17:46:00 +0900",
    "published_at_kst": "2026-05-08T17:46:00+09:00",
    "keyword": "서울 아파트",
    "scraped_at": "2026-05-08T17:57:25.747856+09:00"
  },
  {
    "title": "여름 태풍 보험으로 대비하세요…강북구, 풍수해·지진재해보험 운영",
    "description": "서울 강북구는 여름철 집중호우와 태풍 등 자연재해에 대비해 풍수해·지진재해보험 가입을 독려하기 위한... 단독주택, 공동주택(15층 이하 아파트 포함), 상가주택에 거주하는 소유주와 세입자가 보험 가입 대상이다. 빈집...",
    "url": "https://n.news.naver.com/mnews/article/081/0003642217?sid=102",
    "published_at": "Fri, 08 May 2026 17:44:00 +0900",
    "published_at_kst": "2026-05-08T17:44:00+09:00",
    "keyword": "서울 아파트",
    "scraped_at": "2026-05-08T17:57:25.747856+09:00"
  },
  {
    "title": "건설사, 정원박람회로 모인다…고객 접점·ESG '두마리 토끼' 전략",
    "description": "[김용현 / 대우건설 건축사업본부 상무 : 지난해 보라매 공원에 적용됐던 작품은 작년에 당사의 아파트 단지에 이미 적용을 하였고, 여기 서울숲에 적용된 작품도 추후에 당사 단지에 적용 예정입니다.]ESG 경영과...",
    "url": "https://news.mtn.co.kr/news-detail/2026050816380836256",
    "published_at": "Fri, 08 May 2026 17:42:00 +0900",
    "published_at_kst": "2026-05-08T17:42:00+09:00",
    "keyword": "서울 아파트",
    "scraped_at": "2026-05-08T17:57:25.747856+09:00"
  },
  {
    "title": "[AI 부동산 투데이] 아파트 분양 늘어도 분양가 부담...실수요는 ′고민...",
    "description": "지방 주요 도시들은 물론이고 서울을 비롯한 수도권 핵심 도심에서도 재개발과 재건축 등 정비사업 진행이... 신축 아파트로 이동하고자 하는 욕구가 거세지고 있습니다. 낡은 주거지를 떠나 새집으로 향하려는 대기...",
    "url": "https://www.newspim.com/news/view/20260508001294",
    "published_at": "Fri, 08 May 2026 17:42:00 +0900",
    "published_at_kst": "2026-05-08T17:42:00+09:00",
    "keyword": "서울 아파트",
    "scraped_at": "2026-05-08T17:57:25.747856+09:00"
  },
  {
    "title": "김이탁 국토차관 “안전은 그 무엇과도 바꿀 수 없는 최우선 가치”",
    "description": "밀레니엄 힐튼 해체공사 현장 찾아 안전관리 실태 점검하며 강조 김이탁 국토교통부 1차관이 8일 오후 서울... 김 장관은 지난 4일 세종시 아파트 건설현장을 방문해 자재수급 상황을 긴급 점검하는 자리에서 안전관리...",
    "url": "https://n.news.naver.com/mnews/article/016/0002640920?sid=101",
    "published_at": "Fri, 08 May 2026 17:39:00 +0900",
    "published_at_kst": "2026-05-08T17:39:00+09:00",
    "keyword": "서울 아파트",
    "scraped_at": "2026-05-08T17:57:25.747856+09:00"
  },
  {
    "title": "코스피 최고치에도 충청 집값 제자리",
    "description": "서울 과열 우려와 대조 [충청투데이 함성곤 기자] 충청권 주택시장은 증시 호황으로 불어난 자금이... 대전과 세종, 충남의 아파트값이 보합 또는 하락세를 이어가고, 매수 심리 회복도 더딘 상황에서 주식 차익 실현...",
    "url": "https://www.cctoday.co.kr/news/articleView.html?idxno=2229822",
    "published_at": "Fri, 08 May 2026 17:32:00 +0900",
    "published_at_kst": "2026-05-08T17:32:00+09:00",
    "keyword": "서울 아파트",
    "scraped_at": "2026-05-08T17:57:25.747856+09:00"
  },
  {
    "title": "[필동정담] 역세권 노인주택",
    "description": "경기도 고양시의 신축 아파트에 사시던 장모님은 1년 전 서울 외곽의 역세권 아파트로 옮겼다. 평수는 줄었지만 삶의 만족도는 오히려 높아졌다고 한다. 지하철을 타고 어디든 쉽게 이동할 수 있고, 주변에 젊은 사람이...",
    "url": "https://n.news.naver.com/mnews/article/009/0005677223?sid=110",
    "published_at": "Fri, 08 May 2026 17:32:00 +0900",
    "published_at_kst": "2026-05-08T17:32:00+09:00",
    "keyword": "서울 아파트",
    "scraped_at": "2026-05-08T17:57:25.747856+09:00"
  },
  {
    "title": "[단독] 정원오 '빌라 공급' 논란…성동구 빌라 비중 서울 최하위권",
    "description": "성동구 빌라 비중 9.9%…서울 25개 자치구 내 24위 성동구 아파트 비중 서울 4위…오세훈 측 \"현실 모르고 공급\" 아주경제=고혜영 기자 kohy0321@ajunews.com [그래픽 = 챗GPT] 정원오 더불어민주당 서울시장 후보가 부동산 전...",
    "url": "https://www.ajunews.com/view/20260508154645118",
    "published_at": "Fri, 08 May 2026 17:30:00 +0900",
    "published_at_kst": "2026-05-08T17:30:00+09:00",
    "keyword": "서울 아파트",
    "scraped_at": "2026-05-08T17:57:25.747856+09:00"
  },
  {
    "title": "개포동 아파트 찾은 정원오 “강남 특위 만들어 재건축 속도 낼 것”",
    "description": "정 후보는 이날 오후 재건축 사업이 진행 중인 서울 강남구 개포우성7차아파트를 찾았다. 정 후보는 개포우성아파트 단지 사이를 걸으며 재건축 정비 사업 조합장 등 관계자들과 대화를 나눴다. 이후 인근에 위치한 조합...",
    "url": "https://n.news.naver.com/mnews/article/366/0001162897?sid=162",
    "published_at": "Fri, 08 May 2026 17:29:00 +0900",
    "published_at_kst": "2026-05-08T17:29:00+09:00",
    "keyword": "서울 아파트",
    "scraped_at": "2026-05-08T17:57:25.747856+09:00"
  },
  {
    "title": "캠코, 8,045억 압류재산 1,505건 공매…5월 13일까지 입찰 진행",
    "description": "이 가운데 토지가 734건으로 가장 많았고, 아파트·연립주택·단독주택 등 주거용 건물도 279건 포함됐다. 서울과 경기 등 수도권 소재 주거용 물건만 148건에 달한다. 눈에 띄는 부분은 감정가 70% 이하 물건이 366건...",
    "url": "http://www.newstown.co.kr/news/articleView.html?idxno=702903",
    "published_at": "Fri, 08 May 2026 17:28:00 +0900",
    "published_at_kst": "2026-05-08T17:28:00+09:00",
    "keyword": "서울 아파트",
    "scraped_at": "2026-05-08T17:57:25.747856+09:00"
  },
  {
    "title": "은평 증산5구역, 1906가구 대단지로 탈바꿈",
    "description": "서울 은평구의 노후 주택단지인 증산5구역이 1906가구 대단지로 거듭난다. 증산5구역이 완료되면 수색... 정비사업 계획에 따라 증산5구역은 11만 2804㎡ 부지에 21개 동, 지상 29층, 1906가구 규모 아파트 단지가 조성된다....",
    "url": "https://n.news.naver.com/mnews/article/081/0003642207?sid=101",
    "published_at": "Fri, 08 May 2026 17:26:00 +0900",
    "published_at_kst": "2026-05-08T17:26:00+09:00",
    "keyword": "서울 아파트",
    "scraped_at": "2026-05-08T17:57:25.747856+09:00"
  },
  {
    "title": "규제 피한 실수요···경기 아파트 비규제지역 거래량 '쑥'",
    "description": "8일 부동산 전문 리서치업체 리얼투데이가 국토교통부 실거래가 자료를 토대로 경기도 아파트 매매... 앞서 정부는 지난해 10·15 대책을 통해 서울 전역과 경기 남부 12개 지역을 조정대상지역·투기과열지구와...",
    "url": "https://www.sisajournal-e.com/news/articleView.html?idxno=421002",
    "published_at": "Fri, 08 May 2026 17:26:00 +0900",
    "published_at_kst": "2026-05-08T17:26:00+09:00",
    "keyword": "서울 아파트",
    "scraped_at": "2026-05-08T17:57:25.747856+09:00"
  },
  {
    "title": "양도세 유예 종료 앞두고 서울 집값 다시 '들썩'",
    "description": "양도소득세 중과 유예 종료가 다가오면서 서울 아파트값 상승세가 다시 확대되고 있다. 이번 주에는 강남구를 제외한 서울 모든 자치구에서 아파트값이 일제히 오르며 서울 전역으로 상승 흐름이 확산되는...",
    "url": "https://www.seoulfn.com/news/articleView.html?idxno=628245",
    "published_at": "Fri, 08 May 2026 17:25:00 +0900",
    "published_at_kst": "2026-05-08T17:25:00+09:00",
    "keyword": "서울 아파트",
    "scraped_at": "2026-05-08T17:57:25.747856+09:00"
  },
  {
    "title": "\"전 세대 한강뷰\"…현대건설, 압구정5구역 '승부수'",
    "description": "광폭 파노라마 조망은 최대 폭이 13m으로, 벽체와 프레임의 존재감을 최소화한 설계로 세대 내 거실에서 한강 수변과 서울 도심의 스카이라인을 하나의 연결된 풍경처럼 누릴 수 있다. 17m 하이 필로티는 종전 아파트...",
    "url": "https://n.news.naver.com/mnews/article/031/0001027405?sid=101",
    "published_at": "Fri, 08 May 2026 17:25:00 +0900",
    "published_at_kst": "2026-05-08T17:25:00+09:00",
    "keyword": "서울 아파트",
    "scraped_at": "2026-05-08T17:57:25.747856+09:00"
  },
  {
    "title": "거래·대출·세금 ‘모두 꽁꽁’…전세가 상승, 매매가 상승 ‘뇌관’ ...",
    "description": "전세가율이 60%를 넘어서면 매매가격을 자극한다는 것이 통설인데, 현재 서울 아파트 매매가격 대비 전세가격 비율은 4월 기준 50.09%로 낮다는 것이다. 다만 강북권과 경기도, 인천은 전세가격 비율이 높은 수준이다....",
    "url": "https://www.ekn.kr/web/view.php?key=20260508027263143",
    "published_at": "Fri, 08 May 2026 17:24:00 +0900",
    "published_at_kst": "2026-05-08T17:24:00+09:00",
    "keyword": "서울 아파트",
    "scraped_at": "2026-05-08T17:57:25.747856+09:00"
  },
  {
    "title": "에이스침대, '에이스스퀘어 금천점' 오픈…현대백화점 목동점 리뉴얼 이...",
    "description": "지난 4월에도 서울 양천구 핵심 상권과 대단지 아파트 수요를 잡기 위해 현대백화점 목동점 매장을 리뉴얼 오픈했다. 리뉴얼 매장은 동선과 인테리어를 재구성해 소비자들이 제품을 비교하고 체험을 더욱 쉽게 할 수...",
    "url": "http://www.consumernews.co.kr/news/articleView.html?idxno=755426",
    "published_at": "Fri, 08 May 2026 17:22:00 +0900",
    "published_at_kst": "2026-05-08T17:22:00+09:00",
    "keyword": "서울 아파트",
    "scraped_at": "2026-05-08T17:57:25.747856+09:00"
  },
  {
    "title": "\"파란색만 보면 이 갈린다\"는데... '송파 표심 공략' 공들이는 정원오",
    "description": "ⓒ 정원오캠프 정 후보는 이날 오전 현장최고위에 이어 오후에도 서울 강남 개포우성7차아파트를 찾아 시민 의견을 듣고 현장을 둘러봤다. 조합장들과 만난 정 후보는 \"(재건축에) 시간이 걸리다 보니 집에서 녹물이...",
    "url": "https://n.news.naver.com/mnews/article/047/0002514955?sid=162",
    "published_at": "Fri, 08 May 2026 17:21:00 +0900",
    "published_at_kst": "2026-05-08T17:21:00+09:00",
    "keyword": "서울 아파트",
    "scraped_at": "2026-05-08T17:57:25.747856+09:00"
  },
  {
    "title": "서울 전세난에 뜨는 '옆세권'…구리 집 산 3명 중 1명 '서울사람'",
    "description": "부동산 빅데이터 플랫폼 아실에 따르면 이날 기준 서울 아파트 전세 매물은 1만6240건으로 지난해 10월15일(2만4369건) 대비 33.4% 감소했다. 이에 따라 실수요자들은 서울과 가까운 경기지역으로 눈을 돌리고 있다. 특히...",
    "url": "https://n.news.naver.com/mnews/article/003/0013934132?sid=101",
    "published_at": "Fri, 08 May 2026 17:21:00 +0900",
    "published_at_kst": "2026-05-08T17:21:00+09:00",
    "keyword": "서울 아파트",
    "scraped_at": "2026-05-08T17:57:25.747856+09:00"
  },
  {
    "title": "[2026 지선] \"오세훈이 용산 방치\" vs \"정원오, '닭장 아파트' 강요\"",
    "description": "오 후보는 \"용산국제업무지구는 1000만 시민의 미래 먹거리와 청년 세대가 간절히 원하는 양질의 일자리가 달린 그야말로 몇 안 되는 서울의 마지막 성장판\"이라면서 \"서울을 닭장 아파트촌, 과밀 베드타운 정도로...",
    "url": "https://n.news.naver.com/mnews/article/031/0001027402?sid=100",
    "published_at": "Fri, 08 May 2026 17:20:00 +0900",
    "published_at_kst": "2026-05-08T17:20:00+09:00",
    "keyword": "서울 아파트",
    "scraped_at": "2026-05-08T17:57:25.747856+09:00"
  },
  {
    "title": "아내 살해하고 다리서 뛰어내린 60대, 항소심서 \"평생 속죄\"",
    "description": "국민일보에 따르면, A씨(65)는 지난해 9월 19일 오전 4시쯤 강원도 원주의 한 아파트에서 아내 B씨를 살해했다.... 항소심 결심공판은 서울고법 춘천재판부 형사1부 심리로 열렸다. A씨는 법정에서 \"한순간 잘못된 선택이...",
    "url": "https://lawtalknews.co.kr/article/R15IUXVFYVUD",
    "published_at": "Fri, 08 May 2026 17:20:00 +0900",
    "published_at_kst": "2026-05-08T17:20:00+09:00",
    "keyword": "서울 아파트",
    "scraped_at": "2026-05-08T17:57:25.747856+09:00"
  },
  {
    "title": "의료폐기물 시설 인허가 공무원들, '퇴직후 재취업'…환경단체 '고발'",
    "description": "현재 우리 폐기물 정책의 순서가 그렇게 돼 있습니다. 또 하루 50톤 미만의 폐기물 시설은 환경영향평가를... ◆ 정침귀 > 저도 우연히 알게 됐는데, 이 사업체가 부동산 매물로 나와 있습니다. 그것도 '급매', '초급매'라는...",
    "url": "https://n.news.naver.com/mnews/article/079/0004144985?sid=102",
    "published_at": "Fri, 08 May 2026 17:53:00 +0900",
    "published_at_kst": "2026-05-08T17:53:00+09:00",
    "keyword": "부동산 정책",
    "scraped_at": "2026-05-08T17:57:25.747856+09:00"
  },
  {
    "title": "\"부동산은 사람의 판단과 선택이 작용하는 영역\"",
    "description": "부동산 시장이 빠르게 변화하면서 단순한 정보 전달을 넘어선 '판단의 영역'으로 그 성격이 이동하고 있다. 금리와 정책, 대외 변수에 따라 시장 흐름이 복잡해진 가운데, 고객에게 필요한 것은 단편적인 매물 정보가 아니라...",
    "url": "http://www.newsmaker.or.kr/news/articleView.html?idxno=176868",
    "published_at": "Fri, 08 May 2026 17:42:00 +0900",
    "published_at_kst": "2026-05-08T17:42:00+09:00",
    "keyword": "부동산 정책",
    "scraped_at": "2026-05-08T17:57:25.747856+09:00"
  },
  {
    "title": "[위클리오늘] 부산진구 소식 (5.8)",
    "description": "주요 내용은 부동산 계약 시 유의사항과 필수 확인 사항, 전세사기 피해 유형, 등기사항전부증명서 분석 방법, 정부 지원정책 안내 등으로 구성됐다. 참석자들은 거주 중인 주택의 등기사항전부증명서를 활용해 실전...",
    "url": "http://www.weeklytoday.com/news/articleView.html?idxno=774812",
    "published_at": "Fri, 08 May 2026 17:40:00 +0900",
    "published_at_kst": "2026-05-08T17:40:00+09:00",
    "keyword": "부동산 정책",
    "scraped_at": "2026-05-08T17:57:25.747856+09:00"
  },
  {
    "title": "\"청양의 미래 먹거리는 무엇인가\"…6·3 지방선거, 지역 생존 전략이 최...",
    "description": "침체와 부동산 PF 시장 위축 등의 영향으로 시행사가 프로젝트파이낸싱(PF) 자금 확보에 어려움을 겪고 있다\"며... 최근 선거 국면에서 각종 무상 정책과 현금성 공약이 쏟아지는 것과 관련해서도 지속 가능성에 대한 우려가...",
    "url": "http://www.newsprime.co.kr/news/article.html?no=732846",
    "published_at": "Fri, 08 May 2026 17:36:00 +0900",
    "published_at_kst": "2026-05-08T17:36:00+09:00",
    "keyword": "부동산 정책",
    "scraped_at": "2026-05-08T17:57:25.747856+09:00"
  },
  {
    "title": "배당 늘리고, 자사주 태우고… 주주환원 힘주는 통신업계",
    "description": "1분기는 위약금 면제와 해킹 보상안으로 인한 이동통신매출 감소, 부동산 분양 수익 기저효과가 예상되기 때문이다. KT는 분기 배당 정책을 시행하지만 아직 1분기 배당을 공시하지 않았다. 지난해 1분기 배당은...",
    "url": "https://www.sisaweek.com/news/articleView.html?idxno=235403",
    "published_at": "Fri, 08 May 2026 17:34:00 +0900",
    "published_at_kst": "2026-05-08T17:34:00+09:00",
    "keyword": "부동산 정책",
    "scraped_at": "2026-05-08T17:57:25.747856+09:00"
  },
  {
    "title": "용인특례시, 경기도 체납정리 평가 ‘2년 연속 우수’…행정력 입증",
    "description": "부동산 및 차량 공매, 가택 수색, 동산 압류, 관허사업 제한, 번호판 영치 등 체납 징수 활동한 노력이 높은 평가로 이어졌다는 설명이다. 또 도내 평가를 통해 행정 신뢰도 및 기관 경쟁력 제고에 기여했으며 우수 정책의...",
    "url": "https://www.nspna.com/news/?mode=view&newsid=812306",
    "published_at": "Fri, 08 May 2026 17:30:00 +0900",
    "published_at_kst": "2026-05-08T17:30:00+09:00",
    "keyword": "부동산 정책",
    "scraped_at": "2026-05-08T17:57:25.747856+09:00"
  },
  {
    "title": "코스피 최고치에 집값 불씨 되나",
    "description": "이 같은 이유로 서울 등 수요 과잉 지역은 유동성 유입을 경계하더라도, 침체가 장기화한 지방 부동산 시장에는 선별적인 정책 접근이 필요하다는 목소리도 나온다.정 교수는 \"유동성만으로 시장이 움직이기는 어렵고...",
    "url": "https://www.cctoday.co.kr/news/articleView.html?idxno=2229823",
    "published_at": "Fri, 08 May 2026 17:28:00 +0900",
    "published_at_kst": "2026-05-08T17:28:00+09:00",
    "keyword": "부동산 정책",
    "scraped_at": "2026-05-08T17:57:25.747856+09:00"
  },
  {
    "title": "외신 만난 장동혁 \"한미동맹 국민적 우려 많아…李대통령, 북한에 저자...",
    "description": "그는 \"반 시장적 부동산 정책 고집하고 언론에 징벌적 손해배상 책임을 지우는 미디어법과 인권을 침해하는 법도 계속 만들어지고 있다\"며 \"북한 인권 문제는 정책 테이블서 아예 사라졌다\"고 목소리를 높였다. 그러면서...",
    "url": "https://www.polinews.co.kr/news/articleView.html?idxno=730591",
    "published_at": "Fri, 08 May 2026 17:28:00 +0900",
    "published_at_kst": "2026-05-08T17:28:00+09:00",
    "keyword": "부동산 정책",
    "scraped_at": "2026-05-08T17:57:25.747856+09:00"
  },
  {
    "title": "시중은행 줄고 인터넷은행 늘고…엇갈린 예대금리차, 이유는",
    "description": "정부의 핵심 정책 과제 중 하나인 생산적 금융 확대 기조에 발맞추며 기업대출 금리를 낮춘 결과로... 반면 가계대출 금리는 부동산 규제 영향으로 상승하거나 제한적인 조정에 그쳤다. 신한은행과 우리은행의...",
    "url": "https://www.ceoscoredaily.com/page/view/2026050815070625855",
    "published_at": "Fri, 08 May 2026 17:24:00 +0900",
    "published_at_kst": "2026-05-08T17:24:00+09:00",
    "keyword": "부동산 정책",
    "scraped_at": "2026-05-08T17:57:25.747856+09:00"
  },
  {
    "title": "스타트업과 함께 크는 금융그룹…생산적 금융 '잰걸음'",
    "description": "KB국민은행의 부동산 정보 플랫폼 KB부동산에서 제공하는 '전세안전진단' 서비스가 대표적인 성과다. 이... 우리금융은 디노랩 충북센터를 통해 지방자치단체 정책과 연계한 성장 프로그램을 실시할 계획이다. 같은 달...",
    "url": "http://www.newsdream.kr/news/articleView.html?idxno=112005",
    "published_at": "Fri, 08 May 2026 17:16:00 +0900",
    "published_at_kst": "2026-05-08T17:16:00+09:00",
    "keyword": "부동산 정책",
    "scraped_at": "2026-05-08T17:57:25.747856+09:00"
  },
  {
    "title": "주호영, 추경호 캠프 총괄선대위원장 합류…“보수 결집으로 대구 지켜...",
    "description": "또 문재인 정부 시절 국무총리 이력을 거론하며 “외교·안보와 부동산 정책 실패에 대해 책임 있는 역할을 했는지 묻지 않을 수 없다”고 지적했다. 민주당과 이재명 정부를 겨냥한 공세도 이어졌다. 주 부의장은...",
    "url": "https://n.news.naver.com/mnews/article/031/0001027395?sid=102",
    "published_at": "Fri, 08 May 2026 17:14:00 +0900",
    "published_at_kst": "2026-05-08T17:14:00+09:00",
    "keyword": "부동산 정책",
    "scraped_at": "2026-05-08T17:57:25.747856+09:00"
  },
  {
    "title": "6·3 지방선거: '내란 종식' vs '독재 저지'...탄핵 이후 민심은 어디로",
    "description": "정 후보는 '오세훈 10년 심판'을 내세우며 부동산 공급 병목 해소, 30분 통근도시, 재개발·재건축 속도 향상 등을 공약했다. 이에 오 후보 측은 정원오 후보의 재개발·재건축 공약을 기존 서울시 정책을 포장만 바꾼...",
    "url": "https://www.bbc.com/korean/articles/c2l2ne1vdj2o?xtor=AL-73-%5Bpartner%5D-%5Bnaver%5D-%5Bheadline%5D-%5Bkorean%5D-%5Bbizdev%5D-%5Bisapi%5D",
    "published_at": "Fri, 08 May 2026 17:14:00 +0900",
    "published_at_kst": "2026-05-08T17:14:00+09:00",
    "keyword": "부동산 정책",
    "scraped_at": "2026-05-08T17:57:25.747856+09:00"
  },
  {
    "title": "정책대출 늘린 새마을금고…서민금융 공급 확대",
    "description": "업계에서는 새마을금고가 정책금융 비중을 늘리는 배경으로 안정성 중심 여신 운용 기조를 꼽는다. 부동산 프로젝트파이낸싱(PF) 대출 부실 여파 이후 상호금융권 전반이 여신 포트폴리오 조정에 나선 가운데 정책대출...",
    "url": "http://www.ftoday.co.kr/news/articleView.html?idxno=358633",
    "published_at": "Fri, 08 May 2026 17:12:00 +0900",
    "published_at_kst": "2026-05-08T17:12:00+09:00",
    "keyword": "부동산 정책",
    "scraped_at": "2026-05-08T17:57:25.747856+09:00"
  },
  {
    "title": "[아하!] 다주택자 양도세 중과 유예 종료 \"내 집 마련 기회일까, 매물 잠...",
    "description": "물론 정책의 기대 효과도 분명합니다. 다주택자 양도세 중과는 부동산 투기와 갭투자를 억제하는 데 목적이 있습니다. 다주택 보유에 따른 세 부담을 높이면 투자 수요를 줄이고, 실수요자 중심의 시장을 만들 수 있다는...",
    "url": "http://www.newsprime.co.kr/news/article.html?no=732835",
    "published_at": "Fri, 08 May 2026 17:08:00 +0900",
    "published_at_kst": "2026-05-08T17:08:00+09:00",
    "keyword": "부동산 정책",
    "scraped_at": "2026-05-08T17:57:25.747856+09:00"
  },
  {
    "title": "커지는 ‘매물 잠김’ 우려…정부, 등록임대사업자 ‘양도세 공제’도...",
    "description": "구윤철 부총리 겸 재정경제부 장관은 8일 정부서울청사에서 주재한 경제·부동산관계장관회의에서 “9일 이후 매물 잠김이 나타날 수 있다는 일부의 우려가 있으나, 정부의 정책 의지는 과거와 다르다”며 “대출 규제와...",
    "url": "https://n.news.naver.com/mnews/article/028/0002804295?sid=101",
    "published_at": "Fri, 08 May 2026 17:06:00 +0900",
    "published_at_kst": "2026-05-08T17:06:00+09:00",
    "keyword": "부동산 정책",
    "scraped_at": "2026-05-08T17:57:25.747856+09:00"
  },
  {
    "title": "베이징대 졸업생이 배달 알바...누가 이들을 취업 포기자로 만들었나",
    "description": "중국 정부가 청년 일자리 흡수 능력이 가장 강한 부문인 부동산, 빅테크, 사교육을 규제했기... 한 자녀 정책 세대를 키워온 중산층 부모에게는 자녀가 배달 기사나 공장 노동자가 됐다는 것은 투자...",
    "url": "https://n.news.naver.com/mnews/article/023/0003975366?sid=004",
    "published_at": "Fri, 08 May 2026 17:01:00 +0900",
    "published_at_kst": "2026-05-08T17:01:00+09:00",
    "keyword": "부동산 정책",
    "scraped_at": "2026-05-08T17:57:25.747856+09:00"
  },
  {
    "title": "[사실은 이렇습니다] 정부는 데이터의 부처 간 칸막이를 낮추고 더 빠르...",
    "description": "○ 또한, 부동산 대책 수립을 위한 주택 부채 관련 데이터가 흩어져 공유되지 않고 있어 '주택 부채' 통계가 없다고 보도했습니다. [관계부처 입장] □ 정부는 정책 설계 고도화 및 신규 통계 개발을 위해 데이터 보유...",
    "url": "https://www.korea.kr/briefing/actuallyView.do?newsId=148964109&call_from=naver_news",
    "published_at": "Fri, 08 May 2026 17:00:00 +0900",
    "published_at_kst": "2026-05-08T17:00:00+09:00",
    "keyword": "부동산 정책",
    "scraped_at": "2026-05-08T17:57:25.747856+09:00"
  },
  {
    "title": "케뱅·카뱅, 1Q 이자·비이자 고른 성장…디지털 자산·글로벌 확장 추진",
    "description": "여신 잔액은 47조6990억원으로 정책금융상품, 서민금융상품, 개인사업자 대출을 중심으로 전년 동기 대비 7.... 개인사업자 부동산담보대출 구조를 정교화하고, 자금 용도 서비스 범위를 단계적으로 개선하는 등...",
    "url": "https://www.kfenews.co.kr/news/articleView.html?idxno=657764",
    "published_at": "Fri, 08 May 2026 16:58:00 +0900",
    "published_at_kst": "2026-05-08T16:58:00+09:00",
    "keyword": "부동산 정책",
    "scraped_at": "2026-05-08T17:57:25.747856+09:00"
  },
  {
    "title": "[김능구·차재원의 정국진단 5월②][전문] \"공소 취소 특검법에 보수 결...",
    "description": "그러니까 이게 거의 4：6 수준으로 있으면, 이게 60%를 넘어설 때 그걸 정책으로 밀고 나가야 민심과 같이 가는... 우리가 하려는 건 부동산 투기 잡는 거다. 이런 부분들을 강하게 치고 나가야 되는데 약간은 좀 뭔가...",
    "url": "https://www.polinews.co.kr/news/articleView.html?idxno=730587",
    "published_at": "Fri, 08 May 2026 16:49:00 +0900",
    "published_at_kst": "2026-05-08T16:49:00+09:00",
    "keyword": "부동산 정책",
    "scraped_at": "2026-05-08T17:57:25.747856+09:00"
  },
  {
    "title": "[기획] 홈플러스 고용 안정 해법, 회생자금·제3자 관리·고용승계에 달...",
    "description": "대주주인 MBK파트너스, 최대 채권자로 거론되는 메리츠금융그룹, 회생절차를 관리하는 법원, 정책금융을... MBK가 홈플러스를 인수한 이후 점포 매각, 부동산 유동화, 비용 절감 중심의 경영전략이 이어졌다는 비판이...",
    "url": "http://www.rightknow.co.kr/news/articleView.html?idxno=34053",
    "published_at": "Fri, 08 May 2026 16:46:00 +0900",
    "published_at_kst": "2026-05-08T16:46:00+09:00",
    "keyword": "부동산 정책",
    "scraped_at": "2026-05-08T17:57:25.747856+09:00"
  },
  {
    "title": "[공기업 센터] 한난·HUG·수자원공사",
    "description": "한국부동산원, 한국국토정보공사, 한국교통안전공단 등 국토교통부 산하 8개 공공기관이 참여한다. 이 중... 전환 지원에도 힘쓸 것\"이라며 \"정부의 에너지 전환 정책 이행에도 적극 역할을 해나갈 계획\"이라고 말했다.",
    "url": "http://www.iminju.net/news/articleView.html?idxno=163589",
    "published_at": "Fri, 08 May 2026 16:44:00 +0900",
    "published_at_kst": "2026-05-08T16:44:00+09:00",
    "keyword": "부동산 정책",
    "scraped_at": "2026-05-08T17:57:25.747856+09:00"
  },
  {
    "title": "[이재명·강훈식· 류진 발언, 시장과 민생을 뒤흔들다①] 이재명 대통령...",
    "description": "다주택자 양도소득세 중과 유예 종료가 임박하면서 부동산 시장의 긴장감이 커지고 있다. [사진 = 뉴시스]... 본지와 이야기를 나눈 이은형 대한건설정책연구원 연구위원은 \"양도세 중과유예 폐지는 결국 다주택자 보유...",
    "url": "https://www.ilyoseoul.co.kr/news/articleView.html?idxno=516763",
    "published_at": "Fri, 08 May 2026 16:44:00 +0900",
    "published_at_kst": "2026-05-08T16:44:00+09:00",
    "keyword": "부동산 정책",
    "scraped_at": "2026-05-08T17:57:25.747856+09:00"
  },
  {
    "title": "신계용 과천시장 후보, 시민 제안 공약 1호 ‘경마공원 이전 반대’ 선...",
    "description": "신계용 과천시장 후보가 시민들과 소통하며 직접 발굴한 정책인 ‘과천... 한편, 과천시는 지난 2020년 8·4 부동산 대책 당시 청사 유휴지 주택공급 추진으로 인해...",
    "url": "http://www.breaknews.com/1205884",
    "published_at": "Fri, 08 May 2026 16:42:00 +0900",
    "published_at_kst": "2026-05-08T16:42:00+09:00",
    "keyword": "부동산 정책",
    "scraped_at": "2026-05-08T17:57:25.747856+09:00"
  },
  {
    "title": "농협은행, 1Q 사잇돌대출 1.5억원 그쳐…포용금융 역할론 재부각",
    "description": "공급하는 정책성 상품이다. 금융권에서는 최근 중·저신용자 대상 금융 접근성 확대가 주요 과제로... 특히 최근 상호금융권 전반이 비조합원 중심의 고신용자 대출과 부동산 금융에 치우쳐 있다는 지적이 제기되는...",
    "url": "https://www.1conomynews.co.kr/news/articleView.html?idxno=48483",
    "published_at": "Fri, 08 May 2026 16:38:00 +0900",
    "published_at_kst": "2026-05-08T16:38:00+09:00",
    "keyword": "부동산 정책",
    "scraped_at": "2026-05-08T17:57:25.747856+09:00"
  },
  {
    "title": "한 장에 150만원…포토카드 수익상품 됐다",
    "description": "전문적으로 매매하는 업자가 등장하는 등 포토카드 거래 시장이 과열 양상을 보이고 있다는 지적도 나온다.... 가격이 높은 일부 포카는 ‘반포자이’ ‘한남더힐’ 같은 고급 아파트 이름이 붙어 거래된다. 포카마켓에...",
    "url": "https://n.news.naver.com/mnews/article/015/0005284688?sid=102",
    "published_at": "Fri, 08 May 2026 17:44:00 +0900",
    "published_at_kst": "2026-05-08T17:44:00+09:00",
    "keyword": "아파트 매매",
    "scraped_at": "2026-05-08T17:57:25.747856+09:00"
  },
  {
    "title": "[주간부동산시황] 다주택자 양도세 중과…서울 아파트값 0.27%↑",
    "description": "5월 1주 보합세였던 서울 아파트 매매가격 변동률이 일주일 만에 다시 상승했다. 전셋값도 상승한 가운데 5월 10일 다주택자 양도소득세(양도세) 중과 이후 숨고르기 장세가 이어질 수 있다는 의견이 나온다....",
    "url": "https://n.news.naver.com/mnews/article/119/0003088500?sid=101",
    "published_at": "Fri, 08 May 2026 17:09:00 +0900",
    "published_at_kst": "2026-05-08T17:09:00+09:00",
    "keyword": "아파트 매매",
    "scraped_at": "2026-05-08T17:57:25.747856+09:00"
  },
  {
    "title": "“서울 신축, 나올 때 잡아야”…공급 감소에 분양시장 활기",
    "description": "결국 현재의 인허가 감소는 단순한 수치 변화가 아니라, 향후 서울 신규 아파트 공급 축소를 예고하는... 준공 감소는 곧 실제 입주 가능한 신규 주택 감소를 의미하는 만큼, 전세시장과 기존 매매시장 내 수급 불균형...",
    "url": "http://www.lawissue.co.kr/view.php?ud=20260508170248315567191f6c6e_12",
    "published_at": "Fri, 08 May 2026 17:04:00 +0900",
    "published_at_kst": "2026-05-08T17:04:00+09:00",
    "keyword": "아파트 매매",
    "scraped_at": "2026-05-08T17:57:25.747856+09:00"
  },
  {
    "title": "아파트 규제에 대체재 부상?…오피스텔 '반사효과' 톡톡",
    "description": "전세는 0.24%, 월세는 0.75%로 매매가보다 더 높은 상승률을 보였다. \"아파트 대체재로 거주 가능한 역세권과 준신축을 중심으로 상승했다\"는 게 부동산원의 설명이다. 특히 전국적으로 85㎡ 초과 평형에서만 매매가격이 0.41...",
    "url": "https://www.kpinews.kr/newsView/1065597177189780",
    "published_at": "Fri, 08 May 2026 17:02:00 +0900",
    "published_at_kst": "2026-05-08T17:02:00+09:00",
    "keyword": "아파트 매매",
    "scraped_at": "2026-05-08T17:57:25.747856+09:00"
  },
  {
    "title": "\"지금 아니면 없다\"···서울 아파트 공급절벽 현실화",
    "description": "올해 1분기 서울 주택 인허가와 준공 실적이 동시에 큰 폭으로 감소하면서 향후 신축 아파트 공급 부족... 준공 감소는 곧 입주 가능한 신규 주택 감소로 이어지는 만큼 전세시장과 기존 매매시장의 수급 불균형 우려도...",
    "url": "https://www.smartbizn.com/news/articleView.html?idxno=143456",
    "published_at": "Fri, 08 May 2026 16:56:00 +0900",
    "published_at_kst": "2026-05-08T16:56:00+09:00",
    "keyword": "아파트 매매",
    "scraped_at": "2026-05-08T17:57:25.747856+09:00"
  },
  {
    "title": "신도시 분양시장, ‘중심 상업지역’ 접근성 따라 ‘극과 극’",
    "description": "지난 2022년~2023년 침체기 당시 한국부동산원 아파트 매매가격지수가 약 15.3% (109.5→92.7) 하락했던 경기 화성 동탄2신도시 사례가 대표적이다. 국토교통부 실거래가 자료를 분석한 결과 동탄역 중심상권과 맞닿은...",
    "url": "http://www.lawissue.co.kr/view.php?ud=20260508165519373067191f6c6e_12",
    "published_at": "Fri, 08 May 2026 16:56:00 +0900",
    "published_at_kst": "2026-05-08T16:56:00+09:00",
    "keyword": "아파트 매매",
    "scraped_at": "2026-05-08T17:57:25.747856+09:00"
  },
  {
    "title": "김숙, 4억에 샀던 집 7배 올랐다 “28억이라니…배 아파” (‘홈즈’)",
    "description": "방송인 김숙이 과거 매매했던 아파트의 시세가 크게 오른 것을 확인하고 아쉬워했다. 7일 방송된 MBC ‘구해줘! 홈즈’에는 김숙이 서울 마포구에서 10억 원 미만의 아파트를 찾아나선 모습이 담겼다. 마포구에서 10년...",
    "url": "https://m.entertain.naver.com/article/009/0005677187",
    "published_at": "Fri, 08 May 2026 16:47:00 +0900",
    "published_at_kst": "2026-05-08T16:47:00+09:00",
    "keyword": "아파트 매매",
    "scraped_at": "2026-05-08T17:57:25.747856+09:00"
  },
  {
    "title": "다주택자 양도세 중과 유예 종료, 10일부터 '세금폭탄'",
    "description": "한국부동산원이 발표한 5월 첫째 주(4일 기준) 서울 아파트 매매가격은 전주 대비 0.15% 상승했다. 강서구가 0.30%로 가장 높은 상승률을 기록했고, 성북구(0.27%), 강북구(0.25%), 동대문구(0.24%)가 뒤를 이었다. 매물도...",
    "url": "https://www.thereport.co.kr/news/articleView.html?idxno=87641",
    "published_at": "Fri, 08 May 2026 16:34:00 +0900",
    "published_at_kst": "2026-05-08T16:34:00+09:00",
    "keyword": "아파트 매매",
    "scraped_at": "2026-05-08T17:57:25.747856+09:00"
  },
  {
    "title": "'10일부터 양도세 중과'···9일까지 토지거래허가 신청 가능",
    "description": "최근 10년간 월별 서울 아파트 매매 평균 거래량이 5천5백여 건인 점을 고려하면 지난달에만 평균의 2배 수준으로 계약이 체결된 셈입니다. 녹취> 구윤철 경제부총리 \"다주택자 양도세 중과유예 종료가 지난 1월 23일...",
    "url": "https://www.ktv.go.kr/content/view?content_id=754143",
    "published_at": "Fri, 08 May 2026 16:30:00 +0900",
    "published_at_kst": "2026-05-08T16:30:00+09:00",
    "keyword": "아파트 매매",
    "scraped_at": "2026-05-08T17:57:25.747856+09:00"
  },
  {
    "title": "[이슈+]다주택자 양도세 중과 D-1…막차 매수 몰리고 증여 급증, 서울 집...",
    "description": "한국부동산원 자료에 따르면 5월 1주차 서울 아파트 매매가격지수 상승률은 0.15%를 기록했다. 송파구는 3주 연속 상승했고, 서초구 역시 상승폭을 확대했다. 용산구는 4주 만에 상승 전환한 반면, 강남구는 압구정·개포...",
    "url": "http://www.biztribune.co.kr/news/articleView.html?idxno=353649",
    "published_at": "Fri, 08 May 2026 16:26:00 +0900",
    "published_at_kst": "2026-05-08T16:26:00+09:00",
    "keyword": "아파트 매매",
    "scraped_at": "2026-05-08T17:57:25.747856+09:00"
  },
  {
    "title": "\"왜 내 남편 계약을 네가\"…동료 공인중개사 보복테러한 50대女",
    "description": "판결문에 따르면 공인중개사인 심 씨는 지난해 6월 남편 김모 씨가 아파트를 매매하는 과정에서 자신 몰래 동료 유모(65) 씨의 사무실에서 계약서를 작성한 것을 알게됐다. 이에 격분한 심 씨는 유 씨의 사무실로 향했다....",
    "url": "https://n.news.naver.com/mnews/article/018/0006276081?sid=102",
    "published_at": "Fri, 08 May 2026 16:26:00 +0900",
    "published_at_kst": "2026-05-08T16:26:00+09:00",
    "keyword": "아파트 매매",
    "scraped_at": "2026-05-08T17:57:25.747856+09:00"
  },
  {
    "title": "K-반도체 벨트 수혜 기대감… ‘용인 고림 동문 디 이스트’ 관심 이어...",
    "description": "한국부동산원 자료 기준 용인 처인구 아파트 매매가격지수는 최근 상승 흐름을 이어가며 반도체 산업 배후 주거지로서의 기대감이 반영되는 모습이다. 이 같은 흐름 속에서 동문건설이 공급하는 ‘용인 고림 동문 디...",
    "url": "https://n.news.naver.com/mnews/article/243/0000097561?sid=101",
    "published_at": "Fri, 08 May 2026 16:08:00 +0900",
    "published_at_kst": "2026-05-08T16:08:00+09:00",
    "keyword": "아파트 매매",
    "scraped_at": "2026-05-08T17:57:25.747856+09:00"
  },
  {
    "title": "구윤철 부총리 \"서울 다주택자 아파트, 무주택자가 샀다\"",
    "description": "정부에 따르면 지난 3월 다주택자가 보유한 서울 아파트 매도 물량은 2087건으로 전년대비 32% 증가했다. 이번... 이에 따르면 지난 1월 시장 전문가의 81%는 앞으로 주택매매가격이 상승할 것으로 전망했으나, 지난달엔 56...",
    "url": "https://n.news.naver.com/mnews/article/648/0000046961?sid=101",
    "published_at": "Fri, 08 May 2026 15:54:00 +0900",
    "published_at_kst": "2026-05-08T15:54:00+09:00",
    "keyword": "아파트 매매",
    "scraped_at": "2026-05-08T17:57:25.747856+09:00"
  },
  {
    "title": "\"당첨되면 수억 번다\"…동대문·용산서 또 '줍줍' 나온다",
    "description": "같은 평형대의 매매 거래는 아직 없다. 다만 해당 단지의 84㎡가 지난해 하반기 29억원에 거래된 바 있다.... 호반써밋 에이디션은 국제빌딩주변 제5구역 도시정비형 재개발사업으로 지어진 주상복합 아파트다. 지하...",
    "url": "https://sports.hankooki.com/news/articleView.html?idxno=6932701",
    "published_at": "Fri, 08 May 2026 15:34:00 +0900",
    "published_at_kst": "2026-05-08T15:34:00+09:00",
    "keyword": "아파트 매매",
    "scraped_at": "2026-05-08T17:57:25.747856+09:00"
  },
  {
    "title": "10일부터 양도세 3억 더 낸다 … 중과 면제 막차에 이달 토지거래허가 ...",
    "description": "양도차익 10억원 규모 아파트를 매도한다고 가정하면 3주택자 세 부담은 지방소득세를 포함, 약... 기존에는 유예 마지막 날인 9일까지 매매계약 후 잔금 및 소유권 이전등기까지 완료해야 양도세가 중과되지 않았다....",
    "url": "https://biz.newdaily.co.kr/site/data/html/2026/05/08/2026050800175.html",
    "published_at": "Fri, 08 May 2026 15:20:00 +0900",
    "published_at_kst": "2026-05-08T15:20:00+09:00",
    "keyword": "아파트 매매",
    "scraped_at": "2026-05-08T17:57:25.747856+09:00"
  },
  {
    "title": "다주택자 양도세 유예 종료 D-1…서울 집값 다시 ‘요동’",
    "description": "한국부동산원이 발표한 5월 1주차 주간 아파트 가격 동향에 따르면 서울 아파트 매매가격지수 상승률은 전주 대비 0.01%포인트 오른 0.15%를 기록했다. 특히 송파구는 0.17%로 3주 연속 상승했고, 서초구 역시 상승폭을...",
    "url": "https://www.ekn.kr/web/view.php?key=20260508022243133",
    "published_at": "Fri, 08 May 2026 14:58:00 +0900",
    "published_at_kst": "2026-05-08T14:58:00+09:00",
    "keyword": "아파트 매매",
    "scraped_at": "2026-05-08T17:57:25.747856+09:00"
  },
  {
    "title": "서울 아파트 거래량, 양도세 막차 매물에 반짝 확대",
    "description": "부동산R114가 발표한 5월 2주 전국 아파트 주간 시황에 따르면 국토교통부 실거래가 공개시스템 기준 4월 서울 아파트 매매거래건수는 5789건(8일 기준·계약 해제 제외)이다. 거래 신고 기한이 20일 이상 남았음에도...",
    "url": "http://www.newsprime.co.kr/news/article.html?no=732803",
    "published_at": "Fri, 08 May 2026 14:48:00 +0900",
    "published_at_kst": "2026-05-08T14:48:00+09:00",
    "keyword": "아파트 매매",
    "scraped_at": "2026-05-08T17:57:25.747856+09:00"
  },
  {
    "title": "[주간부동산시황] 전국 0.22% 상승…수도권·지방 모두 올라",
    "description": "한편 지난달 서울 아파트매매거래건수는 5700여 건인 것으로 나타났다. 부동산R114가 국토부 실거래가공개시스템을 분석한 결과 4월 서울 아파트 매매거래건수는 5789건(5월 8일 조사, 계약해제건 제외)으로...",
    "url": "https://www.asiatime.co.kr/article/20260508500217",
    "published_at": "Fri, 08 May 2026 14:42:00 +0900",
    "published_at_kst": "2026-05-08T14:42:00+09:00",
    "keyword": "아파트 매매",
    "scraped_at": "2026-05-08T17:57:25.747856+09:00"
  },
  {
    "title": "김구라 “삼성전자 4만5000원에 샀다” 발언 재조명…보유 시 수익률 50...",
    "description": "홈즈’에는 김구라의 아들 그리가 김숙, 김대호와 동행해 서울 내 매매가 가능한 10억원 미만 아파트 매물을 탐색하는 과정이 담겼다. 그리는 촬영에 앞서 아버지 김구라에게 “왜 강남에 집을 안 샀냐”고 질문했다....",
    "url": "https://n.news.naver.com/mnews/article/366/0001162800?sid=102",
    "published_at": "Fri, 08 May 2026 14:40:00 +0900",
    "published_at_kst": "2026-05-08T14:40:00+09:00",
    "keyword": "아파트 매매",
    "scraped_at": "2026-05-08T17:57:25.747856+09:00"
  },
  {
    "title": "중동 전쟁이 영국 집값 식혔다...설마 한국도?",
    "description": "국내 수급 여건과 대외 리스크의 복합 작용 한국 부동산 시장은 공급 물량 부족, 전세 가격 상승, 대출 규제 등 국내 특유의 변수가 가격 결정에 큰 비중을 차지한다. 특히 공사비 상승으로 인한 신규 공급 위축과 전세 수요...",
    "url": "https://www.etoday.co.kr/news/view/2582870",
    "published_at": "Fri, 08 May 2026 17:44:00 +0900",
    "published_at_kst": "2026-05-08T17:44:00+09:00",
    "keyword": "전세",
    "scraped_at": "2026-05-08T17:57:25.747856+09:00"
  },
  {
    "title": "HUG, 국토부 산하 공공기관과 '전세사기 예방 릴레이 캠페인' 개최",
    "description": "주택도시보증공사(이하 HUG)는 지난 4일 국토교통부 산하 8개 공공기관과 함께 '전세사기 예방 릴레이 캠페인'을 개최했다고 8일 밝혔다. 이번 캠페인은 HUG를 시작으로 5월 한달간 진행된다. 참여기관들은 전세사기 예방...",
    "url": "http://www.enewstoday.co.kr/news/articleView.html?idxno=2427620",
    "published_at": "Fri, 08 May 2026 17:37:00 +0900",
    "published_at_kst": "2026-05-08T17:37:00+09:00",
    "keyword": "전세",
    "scraped_at": "2026-05-08T17:57:25.747856+09:00"
  },
  {
    "title": "기울어진 대구정치에 매운맛을! 진보당 대구시당 4후보 출마 공식화",
    "description": "황순규 진보당 대구시당 위원장은 \"'그 놈이 그 놈'이라는 주민의 매서운 비판에 가계부채 상담, 전세사기 피해자 지원 등 선거기간이 아니어도 민생활동을 이어왔다. 당선되지 않았어도 지역 현안이 없는 일이 되지 않게...",
    "url": "http://worknworld.kctu.org/news/articleView.html?idxno=509227",
    "published_at": "Fri, 08 May 2026 17:28:00 +0900",
    "published_at_kst": "2026-05-08T17:28:00+09:00",
    "keyword": "전세",
    "scraped_at": "2026-05-08T17:57:25.747856+09:00"
  },
  {
    "title": "'시민 1명 중태·127명 무더기 체포' PSG, UCL 결승행 직후 '대규모 폭동...",
    "description": "이후 후반 추가시간, 뮌헨의 해리 케인이 극적인 동점골을 뽑아내며 희망의 불씨를 살렸으나 전세를 뒤집기에는 시간이 부족했다. 결국 경기는 1-1로 종료됐다. PSG의 결승 진출 소식에 기뻐해야 할 프랑스 현지는 축제...",
    "url": "https://m.sports.naver.com/wfootball/article/139/0002246896",
    "published_at": "Fri, 08 May 2026 17:25:00 +0900",
    "published_at_kst": "2026-05-08T17:25:00+09:00",
    "keyword": "전세",
    "scraped_at": "2026-05-08T17:57:25.747856+09:00"
  },
  {
    "title": "보이스피싱·리딩방 사기 급증…위장수사 허용 법안 발의",
    "description": "보이스피싱과 전세사기, 투자 리딩방 사기 등 조직형 사기범죄가 급증하면서 정치권이 '조직사기 특별법... 국토교통부 전세사기피해지원위원회 기준 누적 피해자 인정 건수는 3만8000건을 넘어섰다. 최근 2년간 불법...",
    "url": "http://www.dailypop.kr/news/articleView.html?idxno=98631",
    "published_at": "Fri, 08 May 2026 17:20:00 +0900",
    "published_at_kst": "2026-05-08T17:20:00+09:00",
    "keyword": "전세",
    "scraped_at": "2026-05-08T17:57:25.747856+09:00"
  },
  {
    "title": "[보험업계 소식] ABL생명, KB라이프, 삼성화재, 생명보험사회공헌위원회...",
    "description": "◆생명보험사회공헌위원회, 전세사기피해 청년 학자금대출 상환 사업 지원 생명보험사회공헌위원회는 한국장학재단과 전세사기피해 청년들의 학자금대출 상환 사업에 관한 업무협약을 맺고, 1억원을 지원하기로...",
    "url": "https://www.financialpost.co.kr/news/articleView.html?idxno=258235",
    "published_at": "Fri, 08 May 2026 17:16:00 +0900",
    "published_at_kst": "2026-05-08T17:16:00+09:00",
    "keyword": "전세",
    "scraped_at": "2026-05-08T17:57:25.747856+09:00"
  },
  {
    "title": "전세사기 피해 청년에 학자금 대출 상환 지원",
    "description": "전세사기 피해자(사회초년생) 학자금 대출 원리금 상환 지원 업무협약'을 체결했다고 밝혔습니다. 이번 협약은 생명보험업계에서 공동으로 조성한 사회공헌기금 1억원을 재원으로 합니다. 전세사기 피해 청년들의...",
    "url": "https://n.news.naver.com/mnews/article/374/0000509018?sid=103",
    "published_at": "Fri, 08 May 2026 17:10:00 +0900",
    "published_at_kst": "2026-05-08T17:10:00+09:00",
    "keyword": "전세",
    "scraped_at": "2026-05-08T17:57:25.747856+09:00"
  },
  {
    "title": "생명보험업계, 전세사기 피해자 학자금 대출 상환에 1억 원 지원",
    "description": "생명보험사회공헌위원회는 8일 한국장학재단과 업무협약을 맺고 전세사기 피해 청년의 학자금 대출 상환사업에 1억 원을 지원하기로 했다고 밝혔다. 이번 지원은 청년들의 전세사기 피해가 사회문제로 커지는 가운데...",
    "url": "https://n.news.naver.com/mnews/article/469/0000929728?sid=101",
    "published_at": "Fri, 08 May 2026 17:10:00 +0900",
    "published_at_kst": "2026-05-08T17:10:00+09:00",
    "keyword": "전세",
    "scraped_at": "2026-05-08T17:57:25.747856+09:00"
  },
  {
    "title": "5월9일 알림",
    "description": "◇ 생명보험사회공헌위원회는 한국장학재단과 함께 8일 ‘전세사기피해 청년 학자금대출 상환 사업’을 위한 업무협약을 맺었다. 일반상환 학자금 대출잔액이 100만원 이상인 만 30세 미만 전세사기피해 청년에게...",
    "url": "https://n.news.naver.com/mnews/article/028/0002804298?sid=102",
    "published_at": "Fri, 08 May 2026 17:10:00 +0900",
    "published_at_kst": "2026-05-08T17:10:00+09:00",
    "keyword": "전세",
    "scraped_at": "2026-05-08T17:57:25.747856+09:00"
  },
  {
    "title": "전세사기 피해 청년에 학자금 대출 상환 지원한다",
    "description": "생명보험사회공헌위원회와 '전세사기 피해자(사회초년생) 학자금 대출 원리금 상환 지원 업무협약'을 체결했다고 밝혔다. 이번 협약은 생명보험업계에서 공동으로 조성한 사회공헌기금 1억원을 재원으로 한다. 전세사기...",
    "url": "https://n.news.naver.com/mnews/article/001/0016066490?sid=102",
    "published_at": "Fri, 08 May 2026 17:05:00 +0900",
    "published_at_kst": "2026-05-08T17:05:00+09:00",
    "keyword": "전세",
    "scraped_at": "2026-05-08T17:57:25.747856+09:00"
  },
  {
    "title": "생보사회공헌위, 전세사기 피해 청년…학자금대출 상환에 '1억 지원'",
    "description": "생명보험사회공헌위원회가 전세사기 피해를 입은 청년들의 경제적 재기를 지원하기 위해 학자금대출 상환 지원에 나선다. 전세사기로 인해 사회 진출 초기부터 경제적 어려움을 겪는 청년들의 부담을 덜어주겠다는...",
    "url": "https://www.ezyeconomy.com/news/articleView.html?idxno=235303",
    "published_at": "Fri, 08 May 2026 17:04:00 +0900",
    "published_at_kst": "2026-05-08T17:04:00+09:00",
    "keyword": "전세",
    "scraped_at": "2026-05-08T17:57:25.747856+09:00"
  },
  {
    "title": "LH, 공공기관 통합공시 점검 5년 연속 무벌점…내부통제도 강화",
    "description": "LH는 지난달 특화형 매입임대주택 1000호 규모 공모를 시작했으며 지방 미분양 아파트 매입 설명회와 전세임대형 든든주택 공급도 진행 중이다. 3기 신도시와 공공주택 공급 확대 정책에 맞춰 조직 운영과 공시 관리...",
    "url": "http://www.consumernews.co.kr/news/articleView.html?idxno=755423",
    "published_at": "Fri, 08 May 2026 17:00:00 +0900",
    "published_at_kst": "2026-05-08T17:00:00+09:00",
    "keyword": "전세",
    "scraped_at": "2026-05-08T17:57:25.747856+09:00"
  },
  {
    "title": "생보업계, 전세사기 피해 청년 지원 확대… 학자금대출 상환 돕는다",
    "description": "라이센스뉴스 = 이소라 기자 | 생명보험업계가 전세사기 피해로 이중고를 겪는 청년층 지원에 나섰다. 생명보험사회공헌위원회는 8일 한국장학재단과 업무협약(MOU)을 맺고 전세사기 피해 청년 대상 학자금대출 상환 지원...",
    "url": "https://www.lcnews.co.kr/news/articleView.html?idxno=201872",
    "published_at": "Fri, 08 May 2026 16:56:00 +0900",
    "published_at_kst": "2026-05-08T16:56:00+09:00",
    "keyword": "전세",
    "scraped_at": "2026-05-08T17:57:25.747856+09:00"
  },
  {
    "title": "[현장] 다주택자 양도세 중과 D-2…부동산 시장 ‘폭풍전야’",
    "description": "이날 현장에서는 전세 낀 1주택자 매물 토지거래허가를 신청하려다 돌아가는 등 일부 혼선이 있기도 했다. 정부는 다주택자가 보유한 조정대상지역 주택을 무주택자에게 매도하는 경우에만 실거주 의무를 유예했다....",
    "url": "https://n.news.naver.com/mnews/article/119/0003088492?sid=101",
    "published_at": "Fri, 08 May 2026 16:52:00 +0900",
    "published_at_kst": "2026-05-08T16:52:00+09:00",
    "keyword": "전세",
    "scraped_at": "2026-05-08T17:57:25.747856+09:00"
  },
  {
    "title": "[현장] 소규모 주거용 위반건축물 구제에 나선 이정헌 의원, \"선의의 피...",
    "description": "전세사기 피해자를 위한 별도 지원책도 눈길을 끈다. 피해자가 매입한 주택에 대해서는 부설주차장 설치 의무와 관련 과태료를 면제할 수 있도록 특례 조항을 마련했다. 전세사기 여파로 불가피하게 위반건축물을 떠안은...",
    "url": "https://www.news2day.co.kr/article/20260508500184",
    "published_at": "Fri, 08 May 2026 16:50:00 +0900",
    "published_at_kst": "2026-05-08T16:50:00+09:00",
    "keyword": "전세",
    "scraped_at": "2026-05-08T17:57:25.747856+09:00"
  },
  {
    "title": "[더벨]한국증권·JB운용, 3000억 데이터센터 사모펀드 '맞손'",
    "description": "양사는 기관 전용 부동산 사모펀드 비즈니스를 확대하고 데이터센터 시장 내 투자 주도권을 확보하기 위해... 이를 통해 서울 구로구 개봉동에 위치한 데이터센터 개발 사업 PF에 약 400억원의 투자를 집행한 바 있다....",
    "url": "https://www.thebell.co.kr/free/content/ArticleView.asp?key=202605060756361780103463",
    "published_at": "Fri, 08 May 2026 08:32:00 +0900",
    "published_at_kst": "2026-05-08T08:32:00+09:00",
    "keyword": "개봉동 부동산",
    "scraped_at": "2026-05-08T17:57:25.747856+09:00"
  },
  {
    "title": "강남구 빼고 다 올랐다…서울 아파트값 0.15%↑",
    "description": "7일 한국부동산원의 5월 1주(4일 기준) 전국주택가격동향조사에 따르면 서울 주간 아파트값 상승률은 0.15... 중소형 규모 위주로, 구로구(0.21%)는 구로·개봉동 위주로, 강동구(0.21%)는 암사·명일동 위주로 올랐다.",
    "url": "https://n.news.naver.com/mnews/article/119/0003088195?sid=101",
    "published_at": "Thu, 07 May 2026 21:18:00 +0900",
    "published_at_kst": "2026-05-07T21:18:00+09:00",
    "keyword": "개봉동 부동산",
    "scraped_at": "2026-05-08T17:57:25.747856+09:00"
  }
]